namepull/__init__.py
namepull-0.3.3.dist-info/METADATA
namepull-0.3.3.dist-info/WHEEL
namepull-0.3.3.dist-info/entry_points.txt
namepull-0.3.3.dist-info/RECORD
