Metadata-Version: 2.1
Name: namepull
Version: 0.3.3
Summary: 
License: MIT
Author: Artanicus
Author-email: artanicus@nocturnal.fi
Requires-Python: >=3.8.1,<4.0.0
Classifier: License :: OSI Approved :: MIT License
Classifier: Programming Language :: Python :: 3
Classifier: Programming Language :: Python :: 3.9
Classifier: Programming Language :: Python :: 3.10
Classifier: Programming Language :: Python :: 3.11
Requires-Dist: PyMySQL (>=1.0.2,<2.0.0)
Requires-Dist: absl-py (>=0.13.0,<0.14.0)
Requires-Dist: aiohttp (>=3.7.4,<4.0.0)
Requires-Dist: backoff (>=1.11.1,<2.0.0)
Requires-Dist: python-sql (>=1.2.2,<2.0.0)
